Metadata-Version: 2.1
Name: torc
Version: 0.1.1
Summary: Field and gradient calculations for magnetic coils
Home-page: https://bitbucket.org/cbillington/torc
Author: Chris Billington
Author-email: chrisjbillington@gmail.com
License: BSD
Platform: UNKNOWN
License-File: LICENSE
